web_paging/__init__.py
web_paging/core.py
web_paging/flask_support.py
web_paging/utils.py
web_paging-0.3.0.dist-info/LICENSE
web_paging-0.3.0.dist-info/METADATA
web_paging-0.3.0.dist-info/WHEEL
web_paging-0.3.0.dist-info/top_level.txt
web_paging-0.3.0.dist-info/RECORD
