Metadata-Version: 2.2
Name: web-paging
Version: 0.3.0
Summary: Easy paging for the web.
License: MIT License
Project-URL: Homepage, https://github.com/andycaine/web-paging
Project-URL: Documentation, https://github.com/andycaine/web-paging?tab=readme-ov-file#asaa
Project-URL: Repository, https://github.com/andycaine/web-paging.git
Keywords: paging,Flask
License-File: LICENSE
Requires-Dist: MarkupSafe
Provides-Extra: flask
Requires-Dist: Flask; extra == "flask"
